destlogger/__init__.py
destlogger/logger.py
logger/__init__.py
logger/logger.py
destlogger-1.2.dist-info/METADATA
destlogger-1.2.dist-info/WHEEL
destlogger-1.2.dist-info/top_level.txt
destlogger-1.2.dist-info/RECORD
