Metadata-Version: 2.1
Name: destlogger
Version: 1.2
Summary: UNKNOWN
Home-page: https://github.com/Dest0re/Dest0res-logger
Author: Dest0re
Author-email: dest0re.louisell@gmail.com
License: UNKNOWN
Platform: UNKNOWN
Requires-Dist: colorama
Requires-Dist: cursor
